{"cameraMode":{"drawMode":0,"name":"Shaded","section":"Shading Mode"},"sceneLighting":true,"audioPlay":false,"sceneViewState":{"showFog":false,"showMaterialUpdate":false,"showSkybox":false,"showFlares":false,"showImageEffects":false,"showParticleSystems":false,"showVisualEffectGraphs":true,"m_FxEnabled":true},"in2DMode":false,"pivot":{"x":8.751567840576172,"y":-85.65364074707031,"z":29.446372985839845},"rotation":{"x":-0.5708221793174744,"y":-0.00222521903924644,"z":0.0015333070186898113,"w":-0.821085512638092},"size":135.55349731445313,"orthographic":false}